setuptools_scm_branch_versions/__init__.py
setuptools_scm_branch_versions/version.py
setuptools_scm_branch_versions-0.0.2.dist-info/METADATA
setuptools_scm_branch_versions-0.0.2.dist-info/WHEEL
setuptools_scm_branch_versions-0.0.2.dist-info/entry_points.txt
setuptools_scm_branch_versions-0.0.2.dist-info/RECORD
