Metadata-Version: 2.4
Name: setuptools-scm-branch-versions
Version: 0.0.2
Summary: New version scheme for setuptools-scm
Requires-Python: >=3.8
Requires-Dist: setuptools-scm>=8
